wondoner/interfaces/__init__.py
wondoner/interfaces/enums.py
wondoner/interfaces/interfaces.py
wondoner/interfaces/models.py
wondoner_interfaces-0.1.6.dist-info/licenses/LICENSE
wondoner_interfaces-0.1.6.dist-info/METADATA
wondoner_interfaces-0.1.6.dist-info/WHEEL
wondoner_interfaces-0.1.6.dist-info/top_level.txt
wondoner_interfaces-0.1.6.dist-info/RECORD
