Metadata-Version: 2.4
Name: wondoner-interfaces
Version: 0.1.6
Summary: Interfaces and standard models for the Wondoner plugin system.
License: # Released under MIT License
Classifier: Development Status :: 3 - Alpha
Classifier: Intended Audience :: Developers
Classifier: License :: OSI Approved :: MIT License
Classifier: Operating System :: OS Independent
Classifier: Programming Language :: Python :: 3
Classifier: Programming Language :: Python :: 3.10
Classifier: Programming Language :: Python :: 3.11
Classifier: Programming Language :: Python :: 3.12
Classifier: Typing :: Typed
Requires-Python: >=3.11
License-File: LICENSE
Provides-Extra: test
Requires-Dist: pytest<9.0.0,>=7.0.0; extra == "test"
Requires-Dist: pytest-asyncio<0.24.0,>=0.18.0; extra == "test"
Dynamic: license-file
